helper_functions.py
sz_se_detect.cpython-310-darwin.so
_version.py
ysa_signal.py
signal_analyzer.cpython-310-darwin.so
setup_wizard.py
ysa_signal.dylibs/libhdf5.310.5.1.dylib
ysa_signal.dylibs/libaec.0.1.4.dylib
ysa_signal.dylibs/libhdf5_cpp.310.0.6.dylib
ysa_signal.dylibs/libsz.2.0.1.dylib
ysa_signal-1.2.15.dist-info/RECORD
ysa_signal-1.2.15.dist-info/WHEEL
ysa_signal-1.2.15.dist-info/entry_points.txt
ysa_signal-1.2.15.dist-info/top_level.txt
ysa_signal-1.2.15.dist-info/METADATA
