Metadata-Version: 2.4
Name: ysa-signal
Version: 1.2.15
Summary: YSA Signal - Standalone signal analyzer for .brw/.h5 files
Author-email: Jake Cahoon <jacobbcahoon@gmail.com>
License: MIT
Project-URL: Homepage, https://github.com/ParrishLab/ysa-signal
Project-URL: Repository, https://github.com/ParrishLab/ysa-signal
Project-URL: Issues, https://github.com/ParrishLab/ysa-signal/issues
Keywords: signal processing,neuroscience,electrophysiology,MEA,seizure detection
Classifier: Development Status :: 4 - Beta
Classifier: Intended Audience :: Science/Research
Classifier: Topic :: Scientific/Engineering :: Bio-Informatics
Classifier: License :: OSI Approved :: MIT License
Classifier: Programming Language :: Python :: 3
Classifier: Programming Language :: Python :: 3.6
Classifier: Programming Language :: Python :: 3.7
Classifier: Programming Language :: Python :: 3.8
Classifier: Programming Language :: Python :: 3.9
Classifier: Programming Language :: Python :: 3.10
Classifier: Programming Language :: Python :: 3.11
Classifier: Programming Language :: C++
Classifier: Operating System :: MacOS :: MacOS X
Classifier: Operating System :: Microsoft :: Windows
Requires-Python: >=3.6
Requires-Dist: numpy>=1.19.0
Requires-Dist: h5py>=3.0.0
Requires-Dist: pybind11>=2.6.0
Requires-Dist: matplotlib>=3.3.0
Provides-Extra: dev
Requires-Dist: pytest>=6.0.0; extra == "dev"
Requires-Dist: pytest-cov>=2.10.0; extra == "dev"
